labbdocs/__init__.py
labbdocs/apps.py
labbdocs/content/blog/index.md
labbdocs/content/blog/posts/1_introducing-labb-and-the-roadmap.md
labbdocs/content/icons/1_getting_started/1_introduction.md
labbdocs/content/icons/1_getting_started/2_installation.md
labbdocs/content/icons/1_getting_started/3_quick_start.md
labbdocs/content/icons/2_packs/1_remix.md
labbdocs/content/icons/2_packs/more.md
labbdocs/content/icons/index.md
labbdocs/content/ui/1_getting_started/1_introduction.md
labbdocs/content/ui/1_getting_started/2_installation.md
labbdocs/content/ui/1_getting_started/3_quick_start.md
labbdocs/content/ui/1_getting_started/4_theming.md
labbdocs/content/ui/1_getting_started/5_building_css.md
labbdocs/content/ui/2_references/0_labb_cli.md
labbdocs/content/ui/2_references/1_config_yaml.md
labbdocs/content/ui/2_references/2_django_settings.md
labbdocs/content/ui/2_references/3_lb_tags.md
labbdocs/content/ui/2_references/4_c-lb.m.md
labbdocs/content/ui/2_references/5_llms.txt.md
labbdocs/content/ui/3_components/1_basics/accordion.md
labbdocs/content/ui/3_components/1_basics/alert.md
labbdocs/content/ui/3_components/1_basics/avatar.md
labbdocs/content/ui/3_components/1_basics/badge.md
labbdocs/content/ui/3_components/1_basics/button.md
labbdocs/content/ui/3_components/1_basics/card.md
labbdocs/content/ui/3_components/1_basics/checkbox.md
labbdocs/content/ui/3_components/1_basics/diff.md
labbdocs/content/ui/3_components/1_basics/drawer.md
labbdocs/content/ui/3_components/1_basics/dropdown.md
labbdocs/content/ui/3_components/1_basics/fab.md
labbdocs/content/ui/3_components/1_basics/footer.md
labbdocs/content/ui/3_components/1_basics/link.md
labbdocs/content/ui/3_components/1_basics/menu.md
labbdocs/content/ui/3_components/1_basics/modal.md
labbdocs/content/ui/3_components/1_basics/navbar.md
labbdocs/content/ui/3_components/1_basics/swap.md
labbdocs/content/ui/3_components/1_basics/table.md
labbdocs/content/ui/3_components/1_basics/tabs.md
labbdocs-0.1.0.dist-info/METADATA
labbdocs-0.1.0.dist-info/WHEEL
labbdocs-0.1.0.dist-info/licenses/LICENSE
labbdocs-0.1.0.dist-info/RECORD
