Metadata-Version: 2.4
Name: labbdocs
Version: 0.1.0
Summary: Documentation for the labb project
License: MIT
License-File: LICENSE
Keywords: django,ui,components,library,perfect,django-cotton,tailwind,daisyui
Author: zadiq
Author-email: dev@zadiq.com
Requires-Python: >=3.9,<4
Classifier: Development Status :: 3 - Alpha
Classifier: Intended Audience :: Developers
Classifier: License :: OSI Approved :: MIT License
Classifier: Programming Language :: Python :: 3
Classifier: Programming Language :: Python :: 3 :: Only
Classifier: Programming Language :: Python :: 3.9
Classifier: Programming Language :: Python :: 3.10
Classifier: Programming Language :: Python :: 3.11
Classifier: Programming Language :: Python :: 3.12
Classifier: Programming Language :: Python :: 3.13
Classifier: Framework :: Django
Classifier: Intended Audience :: Developers
Classifier: Operating System :: OS Independent
Requires-Dist: cairosvg (>=2.8.2,<3.0.0)
Requires-Dist: django (>=4.2)
Requires-Dist: django-cotton (>=2.5.0,<3.0.0)
Requires-Dist: markdown (>=3.9,<4.0)
Requires-Dist: python-frontmatter (>=1.1.0,<2.0.0)
Requires-Dist: pyyaml (>=6.0.3,<7.0.0)
Project-URL: Documentation, https://labb.io/
Project-URL: Discussions, https://github.com/labbhq/labb/discussions
Project-URL: Source, https://github.com/labbhq/labb/tree/main/docs
